main.py
IdentityService/__init__.py
IdentityService/service.py
test/__init__.py
test/test_service.py
test_user_auth-1.0.5.dist-info/LICENCE.txt
test_user_auth-1.0.5.dist-info/METADATA
test_user_auth-1.0.5.dist-info/WHEEL
test_user_auth-1.0.5.dist-info/entry_points.txt
test_user_auth-1.0.5.dist-info/top_level.txt
test_user_auth-1.0.5.dist-info/RECORD
