Metadata-Version: 2.1
Name: test-user-auth
Version: 1.0.5
Summary: User authentication service
Home-page: https://github.com/michal-nemec/junior_python_dev_oleksandr_leiko
Author: O.L.
Author-email: leiko.oleksandr@gmail.com
License: UNKNOWN
Platform: UNKNOWN
Classifier: License :: OSI Approved :: MIT License
Classifier: Programming Language :: Python :: 3
Classifier: Programming Language :: Python :: 3.6
Classifier: Programming Language :: Python :: 3.7
Classifier: Programming Language :: Python :: 3.8
Classifier: Programming Language :: Python :: 3.9
Classifier: Programming Language :: Python :: 3 :: Only
Requires-Python: >=3.6
License-File: LICENCE.txt
Requires-Dist: pandas
Requires-Dist: pytest
